lapidary/runtime/__init__.py
lapidary/runtime/_httpx.py
lapidary/runtime/annotations.py
lapidary/runtime/auth.py
lapidary/runtime/client_base.py
lapidary/runtime/http_consts.py
lapidary/runtime/metattype.py
lapidary/runtime/middleware.py
lapidary/runtime/mime.py
lapidary/runtime/model/__init__.py
lapidary/runtime/model/annotations.py
lapidary/runtime/model/api_key.py
lapidary/runtime/model/auth.py
lapidary/runtime/model/error.py
lapidary/runtime/model/op.py
lapidary/runtime/model/param_serialization.py
lapidary/runtime/model/request.py
lapidary/runtime/model/response.py
lapidary/runtime/operation.py
lapidary/runtime/paging.py
lapidary/runtime/py.typed
lapidary/runtime/pycompat.py
lapidary/runtime/type_adapter.py
lapidary/runtime/types_.py
lapidary-0.12.3.dist-info/METADATA
lapidary-0.12.3.dist-info/WHEEL
lapidary-0.12.3.dist-info/RECORD
