Metadata-Version: 2.1
Name: lapidary
Version: 0.12.3
Summary: Python async OpenAPI client library
Home-page: https://github.com/python-lapidary/lapidary
License: MIT
Author: Raphael Krupinski
Author-email: rafalkrupinski@users.noreply.github.com
Requires-Python: >=3.9,<4.0
Classifier: Development Status :: 3 - Alpha
Classifier: Framework :: AsyncIO
Classifier: Intended Audience :: Developers
Classifier: Intended Audience :: Information Technology
Classifier: License :: OSI Approved :: MIT License
Classifier: Operating System :: OS Independent
Classifier: Programming Language :: Python :: 3
Classifier: Programming Language :: Python :: 3.9
Classifier: Programming Language :: Python :: 3.10
Classifier: Programming Language :: Python :: 3.11
Classifier: Programming Language :: Python :: 3.12
Classifier: Programming Language :: Python :: 3.13
Classifier: Topic :: Internet
Classifier: Topic :: Internet :: WWW/HTTP
Classifier: Topic :: Software Development
Classifier: Topic :: Software Development :: Libraries
Classifier: Topic :: Software Development :: Libraries :: Python Modules
Classifier: Typing :: Typed
Requires-Dist: httpx-auth (>=0.22,<0.23)
Requires-Dist: httpx[http2] (>=0.27,<0.28)
Requires-Dist: pydantic (>=2,<3)
Requires-Dist: python-mimeparse (>=2,<3)
Requires-Dist: typing-extensions (>=4.9,<5.0)
Project-URL: Repository, https://github.com/python-lapidary/lapidary
